dhaiconswrap/__init__.py
dhaiconswrap/cameraManager.py
dhaiconswrap/camera_funcion_utils.py
dhaiconswrap/calibrationLib/__init__.py
dhaiconswrap/calibrationLib/calculate_rmsd_kabsch.py
dhaiconswrap/calibrationLib/calibration_function.py
dhaiconswrap/calibrationLib/calibration_kabsch.py
dhaiconswrap/calibrationLib/helper_functions.py
dhaiconswrap/pointclouds_utils/__init__.py
dhaiconswrap/pointclouds_utils/pointclouds_function_utils.py
dhaiconswrap/pointclouds_utils/pointclouds_manager.py
dhaiconswrap-0.2.7.dist-info/LICENSE
dhaiconswrap-0.2.7.dist-info/METADATA
dhaiconswrap-0.2.7.dist-info/WHEEL
dhaiconswrap-0.2.7.dist-info/top_level.txt
dhaiconswrap-0.2.7.dist-info/RECORD
