Metadata-Version: 2.1
Name: dhaiconswrap
Version: 0.2.7
Summary: A depthai wrapper with calibration and points cloud functions
Home-page: https://github.com/AntonioConsiglio/dhaiconswrap
Author: Antonio Consiglio
Author-email: consiglio.antonio.bi@gmail.com
License: MIT
Classifier: Development Status :: 1 - Planning
Classifier: Intended Audience :: Science/Research
Classifier: License :: OSI Approved :: MIT License
Classifier: Operating System :: POSIX :: Linux
Classifier: Operating System :: Microsoft :: Windows :: Windows 10
Classifier: Programming Language :: Python :: 3.8
Classifier: Programming Language :: Python :: 3.9
Classifier: Programming Language :: Python :: 3.10
License-File: LICENSE
Requires-Dist: depthai (==2.17.0.0)
Requires-Dist: numpy (>=1.22.1)
Requires-Dist: opencv-python (>=4.5.5.64)
Requires-Dist: opencv-contrib-python (>=4.5.5.64)
